{
    "magnetometer": {
        "output_data_rate": "200HZ",
        "range": "2G",
        "mode": "continuous",
        "calibration": {
            "x": {
                "offset": 1316.5,
                "scale": 0.000338009
            },
            "y": {
                "offset": 1613.5,
                "scale": 0.000321182
            },
            "z": {
                "offset": -2695.0,
                "scale": 0.000371057
            }
        },
        "oversampling_ratio": "512",
        "declination": {
            "degrees": 3,
            "minutes": 37
        }
    }
}